sequence_detectors/Moore/moore_seq_detector.v
module moore_seq_detector (
    input clk,
    input reset,
    input x,
    output reg z
);

    // State encoding
    localparam S0 = 3'b000;
    localparam S1 = 3'b001;
    localparam S2 = 3'b010;
    localparam S3 = 3'b011;
    localparam S4 = 3'b100;

    reg [2:0] current_state, next_state;

    // State register
    always @(posedge clk or posedge reset) begin
        if (reset)
            current_state <= S0;
        else
            current_state <= next_state;
    end

    // Next state logic
    always @(*) begin
        case (current_state)
            S0: next_state = (x == 1) ? S1 : S0;
            S1: next_state = (x == 0) ? S2 : S1;
            S2: next_state = (x == 1) ? S3 : S0;
            S3: next_state = (x == 1) ? S4 : S2;
            S4: next_state = (x == 1) ? S1 : S2;
            default: next_state = S0;
        endcase
    end

    // Output logic
    always @(*) begin
        z = (current_state == S4) ? 1'b1 : 1'b0;
    end

endmodule

sequence_detectors/Moore/tb_moore_seq_detector.v
module tb_moore_seq_detector;
    reg clk, reset, x;
    wire z;

    moore_seq_detector uut (
        .clk(clk),
        .reset(reset),
        .x(x),
        .z(z)
    );

    reg [15:0] input_pattern = 16'b1101011011010110;
    integer i;

    initial begin
        clk = 0;
        forever #5 clk = ~clk;
    end

    initial begin
        reset = 1; x = 0;
        #10 reset = 0;

        for (i = 15; i >= 0; i = i - 1) begin
            x = input_pattern[i];
            #10;
        end

        #20 $finish;
    end

    initial begin
        $dumpfile("moore_seq_detector.vcd");
        $dumpvars(0, tb_moore_seq_detector);
    end
endmodule

sequence_detectors/Moore/moore_seq_detector.vcd
$date
	Sat Jul 19 23:32:11 2025
$end
$version
	QuestaSim Version 10.7c
$end
$timescale
	1ns
$end

$scope module tb_moore_seq_detector $end
$var reg 1 ! clk $end
$var reg 1 " reset $end
$var reg 1 # x $end
$var wire 1 $ z $end
$var reg 16 % input_pattern [15:0] $end
$var integer 32 & i $end

$scope module uut $end
$var parameter 3 ' S0 $end
$var parameter 3 ( S1 $end
$var parameter 3 ) S2 $end
$var parameter 3 * S3 $end
$var parameter 3 + S4 $end
$var wire 1 , clk $end
$var wire 1 - reset $end
$var wire 1 . x $end
$var reg 1 / z $end
$var reg 3 0 current_state [2:0] $end
$var reg 3 1 next_state [2:0] $end
$upscope $end
$upscope $end
$enddefinitions $end
#0
$dumpvars
0!
1"
0#
0/
b0 0
b0 1
b1101011011010110 %
b0 '
b1 (
b10 )
b11 *
b100 +
bx &
0$
0.
1-
0,
$end
#5
1!
1,
#10
0"
b1111 &
1#
0!
0-
1.
0,
b1 1
#15
1!
1,
b1 0
#20
b1110 &
0!
0,
#25
1!
1,
#30
b1101 &
0#
0!
0.
0,
b10 1
#35
1!
1,
b10 0
b0 1
#40
b1100 &
1#
0!
1.
0,
b11 1
#45
1!
1,
b11 0
b100 1
#50
b1011 &
0#
0!
0.
0,
b10 1
#55
1!
1,
b10 0
b0 1
#60
b1010 &
1#
0!
1.
0,
b11 1
#65
1!
1,
b11 0
b100 1
#70
b1001 &
0!
0,
#75
1!
1,
b100 0
b1 1
1/
1$
#80
b1000 &
0#
0!
0.
0,
b10 1
#85
1!
1,
b10 0
b0 1
0/
0$
#90
b111 &
1#
0!
1.
0,
b11 1
#95
1!
1,
b11 0
b100 1
#100
b110 &
0!
0,
